admissibility_kernel-0.1.0.dist-info/METADATA
admissibility_kernel-0.1.0.dist-info/WHEEL
admissibility_kernel-0.1.0.dist-info/licenses/LICENSE
admissibility_kernel/__init__.py
admissibility_kernel/_admissibility_kernel_rs.abi3.so
admissibility_kernel-0.1.0.dist-info/RECORD
