Metadata-Version: 2.4
Name: admissibility-kernel
Version: 0.1.0
Classifier: Development Status :: 4 - Beta
Classifier: Intended Audience :: Developers
Classifier: License :: OSI Approved :: MIT License
Classifier: Operating System :: OS Independent
Classifier: Programming Language :: Python :: 3
Classifier: Programming Language :: Python :: 3.9
Classifier: Programming Language :: Python :: 3.10
Classifier: Programming Language :: Python :: 3.11
Classifier: Programming Language :: Python :: 3.12
Classifier: Programming Language :: Rust
Classifier: Topic :: Scientific/Engineering :: Artificial Intelligence
License-File: LICENSE
Summary: Deterministic context slicing with cryptographic admissibility verification for conversation DAGs
Keywords: admissibility,graph,context,slicing,dag,conversation
Author: Mohamed Diomande
License: MIT
Requires-Python: >=3.9
Project-URL: Homepage, https://github.com/mohameddiomande/admissibility-kernel
Project-URL: Repository, https://github.com/mohameddiomande/admissibility-kernel
